ArabText.py
README.md
__init__.py
alphabet.py
mapping.py
pyproject.toml
transliterator.py
_types/__init__.py
_types/linked_queue.py
arab_transcription.egg-info/PKG-INFO
arab_transcription.egg-info/SOURCES.txt
arab_transcription.egg-info/dependency_links.txt
arab_transcription.egg-info/top_level.txt
transcription.egg-info/PKG-INFO
transcription.egg-info/SOURCES.txt
transcription.egg-info/dependency_links.txt
transcription.egg-info/top_level.txt
arab_transcription-1.0.0.dist-info/METADATA
arab_transcription-1.0.0.dist-info/WHEEL
arab_transcription-1.0.0.dist-info/top_level.txt
arab_transcription-1.0.0.dist-info/RECORD
