Metadata-Version: 2.1
Name: arab-transcription
Version: 1.0.0
Summary: python script for arabic text transcription
Home-page: https://github.com/Tariha/transcription
Author: Linzo99
Author-email: sallalioune99@gmail.com
